Workbook

Sheet Tour Budget
A1: TM360° UK TOUR BUDGET TEMPLATE
A2: Plan the full financial position before committing to the road.
A3: OFFICIAL
A5: INCOME
A6: Category | B6: Description / Source | C6: Status | D6: Qty | E6: Unit Value (£) | F6: Net (£) | G6: Evidence / Notes | H6: Owner
A7: Show income | B7: Linked from Show Income | F7: ="Show Income"!J36 -> #VALUE!
A8: Merchandise margin | B8: Linked from Merch | F8: =Merch!I26 -> 0
A9: Funding requested | B9: Linked from Assumptions | F9: =Assumptions!B14 -> 0
A10: Artist contribution | B10: Linked from Assumptions | F10: =Assumptions!B15 -> 0
A11: Other confirmed funding | B11: Linked from Assumptions | F11: =Assumptions!B16 -> 0
A12: Sponsorship
A13: Other income
E14: TOTAL INCOME | F14: =SUM(F7:F13) -> #VALUE!
A16: EXPENDITURE
A17: Category | B17: Description / Supplier | C17: Status | D17: Qty | E17: Unit Cost (£) | F17: Net Cost (£) | G17: Quote / Notes | H17: Owner
A18: Tour manager | F18: =IF(OR(D18="",E18=""),0,D18*E18) -> 0
A19: Driver | F19: =IF(OR(D19="",E19=""),0,D19*E19) -> 0
A20: Other crew | F20: =IF(OR(D20="",E20=""),0,D20*E20) -> 0
A21: Artist / musician fees | F21: =IF(OR(D21="",E21=""),0,D21*E21) -> 0
A22: Van hire / vehicle | F22: =IF(OR(D22="",E22=""),0,D22*E22) -> 0
A23: Trailer | F23: =IF(OR(D23="",E23=""),0,D23*E23) -> 0
A24: Fuel | F24: =IF(OR(D24="",E24=""),0,D24*E24) -> 0
A25: Parking / tolls | F25: =IF(OR(D25="",E25=""),0,D25*E25) -> 0
A26: Ferries / flights / rail | F26: =IF(OR(D26="",E26=""),0,D26*E26) -> 0
A27: Accommodation | F27: =IF(OR(D27="",E27=""),0,D27*E27) -> 0
A28: Subsistence / per diems | F28: =IF(OR(D28="",E28=""),0,D28*E28) -> 0
A29: Rehearsal space | F29: =IF(OR(D29="",E29=""),0,D29*E29) -> 0
... A38: Other | F38: =IF(OR(D38="",E38=""),0,D38*E38) -> 0
A39: Contingency | B39: Linked to Assumptions | E39: =Assumptions!B12 -> 0.05 | F39: =SUM(F18:F38)*E39 -> 0
E40: TOTAL COST | F40: =SUM(F18:F39) -> 0
A42: TOUR POSITION
A43: Total income | B43: =F14 -> #VALUE!
A44: Total cost | B44: =F40 -> 0
A45: Surplus / (Shortfall) | B45: =B43-B44 -> #VALUE!
A46: Cost per show | B46: =IF(COUNTA('Show Income'!A6:A35)=0,0,B44/COUNTA('Show Income'!A6:A35)) -> 0
A47: Income per show | B47: =IF(COUNTA('Show Income'!A6:A35)=0,0,B43/COUNTA('Show Income'!A6:A35)) -> 0

Sheet Show Income
A1: SHOW INCOME
A2: Enter one line per show. Use confirmed, provisional or estimated status.
A3: OFFICIAL
A5: Date | B5: Venue | C5: Town / City | D5: Capacity | E5: Deal Type | F5: Guarantee (£) | G5: Ticket Price (£) | H5: Expected Paid | I5: Gross Ticket Income (£) | J5: Expected Artist Income (£) | K5: Status
I6: =IF(OR(G6="",H6=""),0,G6*H6) -> 0 | J6: =IF(E6="Door Split",I6,IF(E6="Guarantee + Split",F6+I6,F6)) -> 0
I7: =IF(OR(G7="",H7=""),0,G7*H7) -> 0 | J7: =IF(E7="Door Split",I7,IF(E7="Guarantee + Split",F7+I7,F7)) -> 0
I8: =IF(OR(G8="",H8=""),0,G8*H8) -> 0 | J8: =IF(E8="Door Split",I8,IF(E8="Guarantee + Split",F8+I8,F8)) -> 0
I9: =IF(OR(G9="",H9=""),0,G9*H9) -> 0 | J9: =IF(E9="Door Split",I9,IF(E9="Guarantee + Split",F9+I9,F9)) -> 0
I10: =IF(OR(G10="",H10=""),0,G10*H10) -> 0 | J10: =IF(E10="Door Split",I10,IF(E10="Guarantee + Split",F10+I10,F10)) -> 0
I11: =IF(OR(G11="",H11=""),0,G11*H11) -> 0 | J11: =IF(E11="Door Split",I11,IF(E11="Guarantee + Split",F11+I11,F11)) -> 0
I12: =IF(OR(G12="",H12=""),0,G12*H12) -> 0 | J12: =IF(E12="Door Split",I12,IF(E12="Guarantee + Split",F12+I12,F12)) -> 0
I13: =IF(OR(G13="",H13=""),0,G13*H13) -> 0 | J13: =IF(E13="Door Split",I13,IF(E13="Guarantee + Split",F13+I13,F13)) -> 0
I14: =IF(OR(G14="",H14=""),0,G14*H14) -> 0 | J14: =IF(E14="Door Split",I14,IF(E14="Guarantee + Split",F14+I14,F14)) -> 0
I15: =IF(OR(G15="",H15=""),0,G15*H15) -> 0 | J15: =IF(E15="Door Split",I15,IF(E15="Guarantee + Split",F15+I15,F15)) -> 0
I16: =IF(OR(G16="",H16=""),0,G16*H16) -> 0 | J16: =IF(E16="Door Split",I16,IF(E16="Guarantee + Split",F16+I16,F16)) -> 0
I17: =IF(OR(G17="",H17=""),0,G17*H17) -> 0 | J17: =IF(E17="Door Split",I17,IF(E17="Guarantee + Split",F17+I17,F17)) -> 0
... I35: =IF(OR(G35="",H35=""),0,G35*H35) -> 0 | J35: =IF(E35="Door Split",I35,IF(E35="Guarantee + Split",F35+I35,F35)) -> 0
H36: TOTAL | J36: =SUM(J6:J35) -> 0

Sheet Merch
A1: MERCHANDISE
A2: Estimate income, venue commission and cost of stock sold.
A3: OFFICIAL
A5: Item | B5: Opening Stock | C5: Unit Cost (£) | D5: Sale Price (£) | E5: Expected Units Sold | F5: Gross Sales (£) | G5: Venue Commission % | H5: Net Sales (£) | I5: Gross Margin (£)
F6: =D6*E6 -> 0 | H6: =F6*(1-G6) -> 0 | I6: =H6-(C6*E6) -> 0
F7: =D7*E7 -> 0 | H7: =F7*(1-G7) -> 0 | I7: =H7-(C7*E7) -> 0
F8: =D8*E8 -> 0 | H8: =F8*(1-G8) -> 0 | I8: =H8-(C8*E8) -> 0
F9: =D9*E9 -> 0 | H9: =F9*(1-G9) -> 0 | I9: =H9-(C9*E9) -> 0
F10: =D10*E10 -> 0 | H10: =F10*(1-G10) -> 0 | I10: =H10-(C10*E10) -> 0
F11: =D11*E11 -> 0 | H11: =F11*(1-G11) -> 0 | I11: =H11-(C11*E11) -> 0
F12: =D12*E12 -> 0 | H12: =F12*(1-G12) -> 0 | I12: =H12-(C12*E12) -> 0
F13: =D13*E13 -> 0 | H13: =F13*(1-G13) -> 0 | I13: =H13-(C13*E13) -> 0
F14: =D14*E14 -> 0 | H14: =F14*(1-G14) -> 0 | I14: =H14-(C14*E14) -> 0
F15: =D15*E15 -> 0 | H15: =F15*(1-G15) -> 0 | I15: =H15-(C15*E15) -> 0
F16: =D16*E16 -> 0 | H16: =F16*(1-G16) -> 0 | I16: =H16-(C16*E16) -> 0
F17: =D17*E17 -> 0 | H17: =F17*(1-G17) -> 0 | I17: =H17-(C17*E17) -> 0
... F25: =D25*E25 -> 0 | H25: =F25*(1-G25) -> 0 | I25: =H25-(C25*E25) -> 0
E26: TOTAL | F26: =SUM(F6:F25) -> 0 | H26: =SUM(H6:H25) -> 0 | I26: =SUM(I6:I25) -> 0

Sheet Cashflow
A1: TOUR CASHFLOW
A2: Record when money is expected in and out, not only the final budget.
A3: OFFICIAL
A5: Date | B5: Type | C5: Category | D5: Description | E5: Expected In (£) | F5: Expected Out (£) | G5: Running Balance (£) | H5: Status
G6: =IF(ROW()=6,E6-F6,G5+E6-F6) -> 0
G7: =IF(ROW()=6,E7-F7,G6+E7-F7) -> 0
G8: =IF(ROW()=6,E8-F8,G7+E8-F8) -> 0
G9: =IF(ROW()=6,E9-F9,G8+E9-F9) -> 0
G10: =IF(ROW()=6,E10-F10,G9+E10-F10) -> 0
G11: =IF(ROW()=6,E11-F11,G10+E11-F11) -> 0
G12: =IF(ROW()=6,E12-F12,G11+E12-F12) -> 0
G13: =IF(ROW()=6,E13-F13,G12+E13-F13) -> 0
G14: =IF(ROW()=6,E14-F14,G13+E14-F14) -> 0
G15: =IF(ROW()=6,E15-F15,G14+E15-F15) -> 0
G16: =IF(ROW()=6,E16-F16,G15+E16-F16) -> 0
G17: =IF(ROW()=6,E17-F17,G16+E17-F17) -> 0
... G45: =IF(ROW()=6,E45-F45,G44+E45-F45) -> 0

Sheet Assumptions
A1: TM360° UK TOUR BUDGET TEMPLATE
A2: Tour controls and assumptions. Blue cells are inputs.
A3: OFFICIAL
A5: TOUR DETAILS
A6: Artist / band
A7: Tour name
A8: Prepared by
A9: Tour start
A10: Tour end
A11: Currency | B11: GBP
A12: Contingency % | B12: 0.05
A13: VAT registered? | B13: No
A14: Funding requested | B14: 0
A15: Artist contribution | B15: 0
A16: Other confirmed funding | B16: 0

Sheet Instructions
A1: HOW TO USE THIS TEMPLATE
A2: A practical starting point, not accountancy or tax advice.
A3: OFFICIAL
A5: WORKFLOW
A6: 1 | B6: Complete the Assumptions sheet first.
A7: 2 | B7: Add each show to Show Income and choose the expected deal type.
A8: 3 | B8: Add merchandise assumptions if merch is part of the plan.
A9: 4 | B9: Complete the expenditure section using quotes where possible.
A10: 5 | B10: Review the surplus or shortfall before confirming the tour.
A11: 6 | B11: Use Cashflow to understand when deposits, hotels, fuel and fees have to be paid.
A12: 7 | B12: Keep evidence links or quote references beside significant costs.
A13: 8 | B13: Update estimated items as they become confirmed.
A15: COLOUR KEY
A16: Blue text | B16: User input
A17: Black text | B17: Formula / calculated value
A18: Green text | B18: Linked from another worksheet
A19: Orange fill | B19: Review or caution
A20: Light red fill | B20: Error or adverse position
